{
  "$schema": "https://schemas.wp.org/trunk/block.json",
  "apiVersion": 3,
  "name": "communikit/error-view",
  "title": "CommuniKit - Error - view",
  "category": "comkb_category_gen",
  "description": "Field for displaying error messages generated by CommuniKit",
  "keywords": [
    "error",
    "view"
  ],
  "textdomain": "communikit",
  "version": "0.1.0",
  "icon": "warning",
  "example": {},
  "supports": {
    "html": false
  },
  "editorScript": "file:./index.js",
  "editorStyle": "file:./index.css"
}